{
  "metadata": {
    "soundFile": "D:\\SIH 2025\\SIH\\3DAvatarSih\\backend\\audios\\video_narration_session_1758656250806_fjkkgfn8t.wav",
    "duration": 21.86
  },
  "mouthCues": [
    { "start": 0.00, "end": 0.08, "value": "X" },
    { "start": 0.08, "end": 0.54, "value": "B" },
    { "start": 0.54, "end": 0.68, "value": "E" },
    { "start": 0.68, "end": 0.82, "value": "B" },
    { "start": 0.82, "end": 0.89, "value": "H" },
    { "start": 0.89, "end": 1.10, "value": "B" },
    { "start": 1.10, "end": 1.17, "value": "F" },
    { "start": 1.17, "end": 1.45, "value": "B" },
    { "start": 1.45, "end": 1.59, "value": "C" },
    { "start": 1.59, "end": 1.73, "value": "B" },
    { "start": 1.73, "end": 1.81, "value": "A" },
    { "start": 1.81, "end": 1.98, "value": "C" },
    { "start": 1.98, "end": 2.12, "value": "G" },
    { "start": 2.12, "end": 2.26, "value": "E" },
    { "start": 2.26, "end": 2.40, "value": "B" },
    { "start": 2.40, "end": 2.47, "value": "C" },
    { "start": 2.47, "end": 2.54, "value": "B" },
    { "start": 2.54, "end": 2.61, "value": "E" },
    { "start": 2.61, "end": 2.82, "value": "B" },
    { "start": 2.82, "end": 2.96, "value": "C" },
    { "start": 2.96, "end": 3.17, "value": "B" },
    { "start": 3.17, "end": 3.28, "value": "A" },
    { "start": 3.28, "end": 3.35, "value": "F" },
    { "start": 3.35, "end": 3.62, "value": "B" },
    { "start": 3.62, "end": 3.97, "value": "C" },
    { "start": 3.97, "end": 4.04, "value": "B" },
    { "start": 4.04, "end": 4.11, "value": "G" },
    { "start": 4.11, "end": 4.25, "value": "X" },
    { "start": 4.25, "end": 4.52, "value": "B" },
    { "start": 4.52, "end": 4.59, "value": "G" },
    { "start": 4.59, "end": 4.73, "value": "C" },
    { "start": 4.73, "end": 5.01, "value": "B" },
    { "start": 5.01, "end": 5.09, "value": "A" },
    { "start": 5.09, "end": 5.38, "value": "C" },
    { "start": 5.38, "end": 5.52, "value": "B" },
    { "start": 5.52, "end": 5.59, "value": "C" },
    { "start": 5.59, "end": 5.80, "value": "B" },
    { "start": 5.80, "end": 5.94, "value": "C" },
    { "start": 5.94, "end": 6.01, "value": "H" },
    { "start": 6.01, "end": 6.08, "value": "C" },
    { "start": 6.08, "end": 6.22, "value": "B" },
    { "start": 6.22, "end": 6.30, "value": "A" },
    { "start": 6.30, "end": 6.60, "value": "B" },
    { "start": 6.60, "end": 6.74, "value": "C" },
    { "start": 6.74, "end": 6.81, "value": "B" },
    { "start": 6.81, "end": 6.95, "value": "E" },
    { "start": 6.95, "end": 7.23, "value": "C" },
    { "start": 7.23, "end": 7.30, "value": "B" },
    { "start": 7.30, "end": 7.38, "value": "A" },
    { "start": 7.38, "end": 7.55, "value": "D" },
    { "start": 7.55, "end": 7.62, "value": "E" },
    { "start": 7.62, "end": 7.83, "value": "B" },
    { "start": 7.83, "end": 7.97, "value": "G" },
    { "start": 7.97, "end": 8.56, "value": "X" },
    { "start": 8.56, "end": 8.61, "value": "B" },
    { "start": 8.61, "end": 8.65, "value": "F" },
    { "start": 8.65, "end": 8.79, "value": "B" },
    { "start": 8.79, "end": 8.86, "value": "G" },
    { "start": 8.86, "end": 9.07, "value": "B" },
    { "start": 9.07, "end": 9.14, "value": "F" },
    { "start": 9.14, "end": 9.21, "value": "H" },
    { "start": 9.21, "end": 9.35, "value": "D" },
    { "start": 9.35, "end": 9.42, "value": "B" },
    { "start": 9.42, "end": 9.56, "value": "G" },
    { "start": 9.56, "end": 9.63, "value": "C" },
    { "start": 9.63, "end": 9.71, "value": "A" },
    { "start": 9.71, "end": 9.94, "value": "E" },
    { "start": 9.94, "end": 10.01, "value": "B" },
    { "start": 10.01, "end": 10.15, "value": "C" },
    { "start": 10.15, "end": 10.23, "value": "A" },
    { "start": 10.23, "end": 10.42, "value": "E" },
    { "start": 10.42, "end": 10.77, "value": "B" },
    { "start": 10.77, "end": 11.02, "value": "X" },
    { "start": 11.02, "end": 11.07, "value": "B" },
    { "start": 11.07, "end": 11.39, "value": "C" },
    { "start": 11.39, "end": 11.47, "value": "A" },
    { "start": 11.47, "end": 11.75, "value": "B" },
    { "start": 11.75, "end": 12.10, "value": "C" },
    { "start": 12.10, "end": 12.17, "value": "E" },
    { "start": 12.17, "end": 12.38, "value": "B" },
    { "start": 12.38, "end": 12.59, "value": "C" },
    { "start": 12.59, "end": 12.80, "value": "B" },
    { "start": 12.80, "end": 12.87, "value": "F" },
    { "start": 12.87, "end": 12.94, "value": "H" },
    { "start": 12.94, "end": 13.01, "value": "C" },
    { "start": 13.01, "end": 13.15, "value": "B" },
    { "start": 13.15, "end": 13.26, "value": "A" },
    { "start": 13.26, "end": 13.39, "value": "C" },
    { "start": 13.39, "end": 13.50, "value": "A" },
    { "start": 13.50, "end": 13.57, "value": "C" },
    { "start": 13.57, "end": 13.85, "value": "B" },
    { "start": 13.85, "end": 13.92, "value": "G" },
    { "start": 13.92, "end": 14.55, "value": "B" },
    { "start": 14.55, "end": 14.83, "value": "F" },
    { "start": 14.83, "end": 15.04, "value": "E" },
    { "start": 15.04, "end": 15.12, "value": "A" },
    { "start": 15.12, "end": 15.35, "value": "E" },
    { "start": 15.35, "end": 15.98, "value": "B" },
    { "start": 15.98, "end": 16.19, "value": "C" },
    { "start": 16.19, "end": 16.26, "value": "G" },
    { "start": 16.26, "end": 16.40, "value": "C" },
    { "start": 16.40, "end": 16.75, "value": "B" },
    { "start": 16.75, "end": 16.82, "value": "G" },
    { "start": 16.82, "end": 17.03, "value": "B" },
    { "start": 17.03, "end": 17.10, "value": "C" },
    { "start": 17.10, "end": 17.19, "value": "A" },
    { "start": 17.19, "end": 17.36, "value": "C" },
    { "start": 17.36, "end": 17.43, "value": "B" },
    { "start": 17.43, "end": 17.51, "value": "A" },
    { "start": 17.51, "end": 17.71, "value": "C" },
    { "start": 17.71, "end": 17.92, "value": "B" },
    { "start": 17.92, "end": 17.99, "value": "G" },
    { "start": 17.99, "end": 18.06, "value": "C" },
    { "start": 18.06, "end": 18.13, "value": "E" },
    { "start": 18.13, "end": 18.20, "value": "B" },
    { "start": 18.20, "end": 18.34, "value": "C" },
    { "start": 18.34, "end": 18.48, "value": "B" },
    { "start": 18.48, "end": 18.69, "value": "C" },
    { "start": 18.69, "end": 18.76, "value": "B" },
    { "start": 18.76, "end": 18.86, "value": "A" },
    { "start": 18.86, "end": 19.05, "value": "D" },
    { "start": 19.05, "end": 19.19, "value": "C" },
    { "start": 19.19, "end": 19.26, "value": "B" },
    { "start": 19.26, "end": 19.33, "value": "C" },
    { "start": 19.33, "end": 19.61, "value": "B" },
    { "start": 19.61, "end": 19.89, "value": "C" },
    { "start": 19.89, "end": 20.03, "value": "E" },
    { "start": 20.03, "end": 20.17, "value": "G" },
    { "start": 20.17, "end": 20.52, "value": "B" },
    { "start": 20.52, "end": 20.66, "value": "C" },
    { "start": 20.66, "end": 21.15, "value": "B" },
    { "start": 21.15, "end": 21.57, "value": "H" },
    { "start": 21.57, "end": 21.85, "value": "B" },
    { "start": 21.85, "end": 21.86, "value": "X" }
  ]
}
